{
   "asset" : {
      "tilesetVersion" : "1.2.3",
      "version" : "0.0"
   },
   "properties" : null,
   "root" : {
      "boundingVolume" : {
         "box" : [
            -9268.11328125,
            4475.4287109375,
            28.805448532104492,
            40.1845703125,
            0.0,
            0.0,
            0.0,
            75.511474609375,
            0.0,
            0.0,
            0.0,
            21.795354843139648
         ]
      },
      "children" : [
         {
            "boundingVolume" : {
               "box" : [
                  -9268.11328125,
                  4475.4287109375,
                  28.805448532104492,
                  40.1845703125,
                  0.0,
                  0.0,
                  0.0,
                  75.511474609375,
                  0.0,
                  0.0,
                  0.0,
                  21.795354843139648
               ]
            },
            "children" : [
               {
                  "boundingVolume" : {
                     "box" : [
                        -9268.11328125,
                        4475.4287109375,
                        28.805448532104492,
                        40.1845703125,
                        0.0,
                        0.0,
                        0.0,
                        75.511474609375,
                        0.0,
                        0.0,
                        0.0,
                        21.795354843139648
                     ]
                  },
                  "children" : [
                     {
                        "boundingVolume" : {
                           "box" : [
                              -9268.11328125,
                              4475.4287109375,
                              28.805448532104492,
                              40.1845703125,
                              0.0,
                              0.0,
                              0.0,
                              75.511474609375,
                              0.0,
                              0.0,
                              0.0,
                              21.795354843139648
                           ]
                        },
                        "children" : [
                           {
                              "boundingVolume" : {
                                 "box" : [
                                    -9268.11328125,
                                    4475.4287109375,
                                    29.129430770874023,
                                    40.1845703125,
                                    0.0,
                                    0.0,
                                    0.0,
                                    75.511474609375,
                                    0.0,
                                    0.0,
                                    0.0,
                                    22.11933708190918
                                 ]
                              },
                              "children" : [
                                 {
                                    "boundingVolume" : {
                                       "box" : [
                                          -9268.115234375,
                                          4437.8037109375,
                                          32.023185729980469,
                                          40.1826171875,
                                          0.0,
                                          0.0,
                                          0.0,
                                          37.886474609375,
                                          0.0,
                                          0.0,
                                          0.0,
                                          19.663541793823242
                                       ]
                                    },
                                    "children" : [
                                       {
                                          "boundingVolume" : {
                                             "box" : [
                                                -9288.1171875,
                                                4418.9951171875,
                                                19.974618911743164,
                                                20.14501953125,
                                                0.0,
                                                0.0,
                                                0.0,
                                                19.054931640625,
                                                0.0,
                                                0.0,
                                                0.0,
                                                6.7796730995178223
                                             ]
                                          },
                                          "children" : [
                                             {
                                                "boundingVolume" : {
                                                   "box" : [
                                                      -9298.072265625,
                                                      4409.58544921875,
                                                      20.022233963012695,
                                                      10.18994140625,
                                                      0.0,
                                                      0.0,
                                                      0.0,
                                                      9.64501953125,
                                                      0.0,
                                                      0.0,
                                                      0.0,
                                                      6.230384349822998
                                                   ]
                                                },
                                                "content" : {
                                                   "uri" : "Tile_+000_+041_L21_0000000.b3dm"
                                                },
                                                "geometricError" : 0.75771111249923706,
                                                "refine" : "REPLACE"
                                             },
                                             {
                                                "boundingVolume" : {
                                                   "box" : [
                                                      -9298.072265625,
                                                      4428.546875,
                                                      17.012109756469727,
                                                      10.18994140625,
                                                      0.0,
                                                      0.0,
                                                      0.0,
                                                      9.441162109375,
                                                      0.0,
                                                      0.0,
                                                      0.0,
                                                      3.3914542198181152
                                                   ]
                                                },
                                                "content" : {
                                                   "uri" : "Tile_+000_+041_L21_0000010.b3dm"
                                                },
                                                "geometricError" : 0.75771111249923706,
                                                "refine" : "REPLACE"
                                             },
                                             {
                                                "boundingVolume" : {
                                                   "box" : [
                                                      -9278.0205078125,
                                                      4409.58544921875,
                                                      20.010154724121094,
                                                      9.986328125,
                                                      0.0,
                                                      0.0,
                                                      0.0,
                                                      9.64501953125,
                                                      0.0,
                                                      0.0,
                                                      0.0,
                                                      6.7441372871398926
                                                   ]
                                                },
                                                "content" : {
                                                   "uri" : "Tile_+000_+041_L21_0000020.b3dm"
                                                },
                                                "geometricError" : 0.75771111249923706,
                                                "refine" : "REPLACE"
                                             },
                                             {
                                                "boundingVolume" : {
                                                   "box" : [
                                                      -9278.0205078125,
                                                      4428.546875,
                                                      16.494729995727539,
                                                      9.986328125,
                                                      0.0,
                                                      0.0,
                                                      0.0,
                                                      9.441162109375,
                                                      0.0,
                                                      0.0,
                                                      0.0,
                                                      3.2981724739074707
                                                   ]
                                                },
                                                "content" : {
                                                   "uri" : "Tile_+000_+041_L21_0000030.b3dm"
                                                },
                                                "geometricError" : 0.75771111249923706,
                                                "refine" : "REPLACE"
                                             }
                                          ],
                                          "content" : {
                                             "uri" : "Tile_+000_+041_L20_000000t3.b3dm"
                                          },
                                          "geometricError" : 1.5154222249984741,
                                          "refine" : "REPLACE"
                                       },
                                       {
                                          "boundingVolume" : {
                                             "box" : [
                                                -9288.1171875,
                                                4456.6826171875,
                                                16.937702178955078,
                                                20.14501953125,
                                                0.0,
                                                0.0,
                                                0.0,
                                                18.882568359375,
                                                0.0,
                                                0.0,
                                                0.0,
                                                4.6480507850646973
                                             ]
                                          },
                                          "children" : [
                                             {
                                                "boundingVolume" : {
                                                   "box" : [
                                                      -9298.072265625,
                                                      4447.30419921875,
                                                      16.860214233398438,
                                                      10.18994140625,
                                                      0.0,
                                                      0.0,
                                                      0.0,
                                                      9.44140625,
                                                      0.0,
                                                      0.0,
                                                      0.0,
                                                      3.6113343238830566
                                                   ]
                                                },
                                                "content" : {
                                                   "uri" : "Tile_+000_+041_L21_0000100.b3dm"
                                                },
                                                "geometricError" : 0.70767837762832642,
                                                "refine" : "REPLACE"
                                             },
                                             {
                                                "boundingVolume" : {
                                                   "box" : [
                                                      -9298.072265625,
                                                      4466.0615234375,
                                                      16.584613800048828,
                                                      10.18994140625,
                                                      0.0,
                                                      0.0,
                                                      0.0,
                                                      9.441162109375,
                                                      0.0,
                                                      0.0,
                                                      0.0,
                                                      3.5456399917602539
                                                   ]
                                                },
                                                "content" : {
                                                   "uri" : "Tile_+000_+041_L21_0000110.b3dm"
                                                },
                                                "geometricError" : 0.70767837762832642,
                                                "refine" : "REPLACE"
                                             },
                                             {
                                                "boundingVolume" : {
                                                   "box" : [
                                                      -9278.0205078125,
                                                      4447.30419921875,
                                                      15.812553405761719,
                                                      9.986328125,
                                                      0.0,
                                                      0.0,
                                                      0.0,
                                                      9.44140625,
                                                      0.0,
                                                      0.0,
                                                      0.0,
                                                      3.5229029655456543
                                                   ]
                                                },
                                                "content" : {
                                                   "uri" : "Tile_+000_+041_L21_0000120.b3dm"
                                                },
                                                "geometricError" : 0.70767837762832642,
                                                "refine" : "REPLACE"
                                             },
                                             {
                                                "boundingVolume" : {
                                                   "box" : [
                                                      -9278.0205078125,
                                                      4466.0615234375,
                                                      17.35255241394043,
                                                      9.986328125,
                                                      0.0,
                                                      0.0,
                                                      0.0,
                                                      9.441162109375,
                                                      0.0,
                                                      0.0,
                                                      0.0,
                                                      4.2547817230224609
                                                   ]
                                                },
                                                "content" : {
                                                   "uri" : "Tile_+000_+041_L21_0000130.b3dm"
                                                },
                                                "geometricError" : 0.70767837762832642,
                                                "refine" : "REPLACE"
                                             }
                                          ],
                                          "content" : {
                                             "uri" : "Tile_+000_+041_L20_000010t3.b3dm"
                                          },
                                          "geometricError" : 1.4153567552566528,
                                          "refine" : "REPLACE"
                                       },
                                       {
                                          "boundingVolume" : {
                                             "box" : [
                                                -9248.0771484375,
                                                4418.98388671875,
                                                32.559059143066406,
                                                20.14453125,
                                                0.0,
                                                0.0,
                                                0.0,
                                                19.06640625,
                                                0.0,
                                                0.0,
                                                0.0,
                                                19.413419723510742
                                             ]
                                          },
                                          "children" : [
                                             {
                                                "boundingVolume" : {
                                                   "box" : [
                                                      -9258.173828125,
                                                      4409.58544921875,
                                                      16.359336853027344,
                                                      9.98583984375,
                                                      0.0,
                                                      0.0,
                                                      0.0,
                                                      9.64501953125,
                                                      0.0,
                                                      0.0,
                                                      0.0,
                                                      3.2181010246276855
                                                   ]
                                                },
                                                "content" : {
                                                   "uri" : "Tile_+000_+041_L21_0000200.b3dm"
                                                },
                                                "geometricError" : 0.70329958200454712,
                                                "refine" : "REPLACE"
                                             },
                                             {
                                                "boundingVolume" : {
                                                   "box" : [
                                                      -9258.173828125,
                                                      4428.546875,
                                                      17.007753372192383,
                                                      9.98583984375,
                                                      0.0,
                                                      0.0,
                                                      0.0,
                                                      9.441162109375,
                                                      0.0,
                                                      0.0,
                                                      0.0,
                                                      3.815453052520752
                                                   ]
                                                },
                                                "content" : {
                                                   "uri" : "Tile_+000_+041_L21_0000210.b3dm"
                                                },
                                                "geometricError" : 0.70329958200454712,
                                                "refine" : "REPLACE"
                                             },
                                             {
                                                "boundingVolume" : {
                                                   "box" : [
                                                      -9235.052734375,
                                                      4400.712890625,
                                                      42.300315856933594,
                                                      1.1201171875,
                                                      0.0,
                                                      0.0,
                                                      0.0,
                                                      0.7724609375,
                                                      0.0,
                                                      0.0,
                                                      0.0,
                                                      9.6721649169921875
                                                   ]
                                                },
                                                "content" : {
                                                   "uri" : "Tile_+000_+041_L21_0000220.b3dm"
                                                },
                                                "geometricError" : 0.70329958200454712,
                                                "refine" : "REPLACE"
                                             },
                                             {
                                                "boundingVolume" : {
                                                   "box" : [
                                                      -9238.123046875,
                                                      4409.58544921875,
                                                      23.080986022949219,
                                                      10.18994140625,
                                                      0.0,
                                                      0.0,
                                                      0.0,
                                                      9.64501953125,
                                                      0.0,
                                                      0.0,
                                                      0.0,
                                                      9.6721658706665039
                                                   ]
                                                },
                                                "content" : {
                                                   "uri" : "Tile_+000_+041_L21_0000230.b3dm"
                                                },
                                                "geometricError" : 0.70329958200454712,
                                                "refine" : "REPLACE"
                                             },
                                             {
                                                "boundingVolume" : {
                                                   "box" : [
                                                      -9238.123046875,
                                                      4428.546875,
                                                      19.865385055541992,
                                                      10.18994140625,
                                                      0.0,
                                                      0.0,
                                                      0.0,
                                                      9.441162109375,
                                                      0.0,
                                                      0.0,
                                                      0.0,
                                                      5.5058441162109375
                                                   ]
                                                },
                                                "content" : {
                                                   "uri" : "Tile_+000_+041_L21_0000240.b3dm"
                                                },
                                                "geometricError" : 0.70329958200454712,
                                                "refine" : "REPLACE"
                                             }
                                          ],
                                          "content" : {
                                             "uri" : "Tile_+000_+041_L20_000020t4.b3dm"
                                          },
                                          "geometricError" : 1.4065991640090942,
                                          "refine" : "REPLACE"
                                       },
                                       {
                                          "boundingVolume" : {
                                             "box" : [
                                                -9248.0771484375,
                                                4456.6826171875,
                                                20.135391235351563,
                                                20.14453125,
                                                0.0,
                                                0.0,
                                                0.0,
                                                18.882568359375,
                                                0.0,
                                                0.0,
                                                0.0,
                                                6.6078243255615234
                                             ]
                                          },
                                          "children" : [
                                             {
                                                "boundingVolume" : {
                                                   "box" : [
                                                      -9258.173828125,
                                                      4447.30419921875,
                                                      18.530059814453125,
                                                      9.98583984375,
                                                      0.0,
                                                      0.0,
                                                      0.0,
                                                      9.44140625,
                                                      0.0,
                                                      0.0,
                                                      0.0,
                                                      5.0375442504882813
                                                   ]
                                                },
                                                "content" : {
                                                   "uri" : "Tile_+000_+041_L21_0000300.b3dm"
                                                },
                                                "geometricError" : 0.72255855798721313,
                                                "refine" : "REPLACE"
                                             },
                                             {
                                                "boundingVolume" : {
                                                   "box" : [
                                                      -9258.173828125,
                                                      4466.0615234375,
                                                      18.145008087158203,
                                                      9.98583984375,
                                                      0.0,
                                                      0.0,
                                                      0.0,
                                                      9.441162109375,
                                                      0.0,
                                                      0.0,
                                                      0.0,
                                                      3.7758851051330566
                                                   ]
                                                },
                                                "content" : {
                                                   "uri" : "Tile_+000_+041_L21_0000310.b3dm"
                                                },
                                                "geometricError" : 0.72255855798721313,
                                                "refine" : "REPLACE"
                                             },
                                             {
                                                "boundingVolume" : {
                                                   "box" : [
                                                      -9238.123046875,
                                                      4447.30419921875,
                                                      19.792695999145508,
                                                      10.18994140625,
                                                      0.0,
                                                      0.0,
                                                      0.0,
                                                      9.44140625,
                                                      0.0,
                                                      0.0,
                                                      0.0,
                                                      5.2941803932189941
                                                   ]
                                                },
                                                "content" : {
                                                   "uri" : "Tile_+000_+041_L21_0000320.b3dm"
                                                },
                                                "geometricError" : 0.72255855798721313,
                                                "refine" : "REPLACE"
                                             },
                                             {
                                                "boundingVolume" : {
                                                   "box" : [
                                                      -9238.123046875,
                                                      4466.0615234375,
                                                      20.578716278076172,
                                                      10.18994140625,
                                                      0.0,
                                                      0.0,
                                                      0.0,
                                                      9.441162109375,
                                                      0.0,
                                                      0.0,
                                                      0.0,
                                                      6.221837043762207
                                                   ]
                                                },
                                                "content" : {
                                                   "uri" : "Tile_+000_+041_L21_0000330.b3dm"
                                                },
                                                "geometricError" : 0.72255855798721313,
                                                "refine" : "REPLACE"
                                             }
                                          ],
                                          "content" : {
                                             "uri" : "Tile_+000_+041_L20_000030t3.b3dm"
                                          },
                                          "geometricError" : 1.4451171159744263,
                                          "refine" : "REPLACE"
                                       }
                                    ],
                                    "content" : {
                                       "uri" : "Tile_+000_+041_L19_00000t3.b3dm"
                                    },
                                    "geometricError" : 5.6244335174560547,
                                    "refine" : "REPLACE"
                                 },
                                 {
                                    "boundingVolume" : {
                                       "box" : [
                                          -9268.09765625,
                                          4513.0654296875,
                                          17.330110549926758,
                                          40.16455078125,
                                          0.0,
                                          0.0,
                                          0.0,
                                          37.875,
                                          0.0,
                                          0.0,
                                          0.0,
                                          10.320016860961914
                                       ]
                                    },
                                    "children" : [
                                       {
                                          "boundingVolume" : {
                                             "box" : [
                                                -9288.1171875,
                                                4494.1982421875,
                                                17.378582000732422,
                                                20.14501953125,
                                                0.0,
                                                0.0,
                                                0.0,
                                                18.882568359375,
                                                0.0,
                                                0.0,
                                                0.0,
                                                10.26812744140625
                                             ]
                                          },
                                          "children" : [
                                             {
                                                "boundingVolume" : {
                                                   "box" : [
                                                      -9298.072265625,
                                                      4484.8193359375,
                                                      14.91429328918457,
                                                      10.18994140625,
                                                      0.0,
                                                      0.0,
                                                      0.0,
                                                      9.44140625,
                                                      0.0,
                                                      0.0,
                                                      0.0,
                                                      1.8388233184814453
                                                   ]
                                                },
                                                "content" : {
                                                   "uri" : "Tile_+000_+041_L21_0001000.b3dm"
                                                },
                                                "geometricError" : 0.69111907482147217,
                                                "refine" : "REPLACE"
                                             },
                                             {
                                                "boundingVolume" : {
                                                   "box" : [
                                                      -9298.072265625,
                                                      4503.57666015625,
                                                      11.066492080688477,
                                                      10.18994140625,
                                                      0.0,
                                                      0.0,
                                                      0.0,
                                                      9.44140625,
                                                      0.0,
                                                      0.0,
                                                      0.0,
                                                      3.9539542198181152
                                                   ]
                                                },
                                                "content" : {
                                                   "uri" : "Tile_+000_+041_L21_0001010.b3dm"
                                                },
                                                "geometricError" : 0.69111907482147217,
                                                "refine" : "REPLACE"
                                             },
                                             {
                                                "boundingVolume" : {
                                                   "box" : [
                                                      -9278.0205078125,
                                                      4484.8193359375,
                                                      20.509407043457031,
                                                      9.986328125,
                                                      0.0,
                                                      0.0,
                                                      0.0,
                                                      9.44140625,
                                                      0.0,
                                                      0.0,
                                                      0.0,
                                                      7.1129097938537598
                                                   ]
                                                },
                                                "content" : {
                                                   "uri" : "Tile_+000_+041_L21_0001020.b3dm"
                                                },
                                                "geometricError" : 0.69111907482147217,
                                                "refine" : "REPLACE"
                                             },
                                             {
                                                "boundingVolume" : {
                                                   "box" : [
                                                      -9278.0205078125,
                                                      4503.57666015625,
                                                      18.541738510131836,
                                                      9.986328125,
                                                      0.0,
                                                      0.0,
                                                      0.0,
                                                      9.44140625,
                                                      0.0,
                                                      0.0,
                                                      0.0,
                                                      5.016693115234375
                                                   ]
                                                },
                                                "content" : {
                                                   "uri" : "Tile_+000_+041_L21_0001030.b3dm"
                                                },
                                                "geometricError" : 0.69111907482147217,
                                                "refine" : "REPLACE"
                                             }
                                          ],
                                          "content" : {
                                             "uri" : "Tile_+000_+041_L20_000100t3.b3dm"
                                          },
                                          "geometricError" : 1.3822381496429443,
                                          "refine" : "REPLACE"
                                       },
                                       {
                                          "boundingVolume" : {
                                             "box" : [
                                                -9288.1171875,
                                                4531.8857421875,
                                                15.97891902923584,
                                                20.14501953125,
                                                0.0,
                                                0.0,
                                                0.0,
                                                19.054931640625,
                                                0.0,
                                                0.0,
                                                0.0,
                                                8.9688253402709961
                                             ]
                                          },
                                          "children" : [
                                             {
                                                "boundingVolume" : {
                                                   "box" : [
                                                      -9298.072265625,
                                                      4522.333984375,
                                                      13.861518859863281,
                                                      10.18994140625,
                                                      0.0,
                                                      0.0,
                                                      0.0,
                                                      9.441162109375,
                                                      0.0,
                                                      0.0,
                                                      0.0,
                                                      6.8514251708984375
                                                   ]
                                                },
                                                "content" : {
                                                   "uri" : "Tile_+000_+041_L21_0001100.b3dm"
                                                },
                                                "geometricError" : 0.76346081495285034,
                                                "refine" : "REPLACE"
                                             },
                                             {
                                                "boundingVolume" : {
                                                   "box" : [
                                                      -9298.072265625,
                                                      4541.29541015625,
                                                      14.062909126281738,
                                                      10.18994140625,
                                                      0.0,
                                                      0.0,
                                                      0.0,
                                                      9.64501953125,
                                                      0.0,
                                                      0.0,
                                                      0.0,
                                                      6.9689016342163086
                                                   ]
                                                },
                                                "content" : {
                                                   "uri" : "Tile_+000_+041_L21_0001110.b3dm"
                                                },
                                                "geometricError" : 0.76346081495285034,
                                                "refine" : "REPLACE"
                                             },
                                             {
                                                "boundingVolume" : {
                                                   "box" : [
                                                      -9278.0205078125,
                                                      4522.333984375,
                                                      19.133371353149414,
                                                      9.986328125,
                                                      0.0,
                                                      0.0,
                                                      0.0,
                                                      9.441162109375,
                                                      0.0,
                                                      0.0,
                                                      0.0,
                                                      4.6266217231750488
                                                   ]
                                                },
                                                "content" : {
                                                   "uri" : "Tile_+000_+041_L21_0001120.b3dm"
                                                },
                                                "geometricError" : 0.76346081495285034,
                                                "refine" : "REPLACE"
                                             },
                                             {
                                                "boundingVolume" : {
                                                   "box" : [
                                                      -9278.0205078125,
                                                      4541.29541015625,
                                                      19.261274337768555,
                                                      9.986328125,
                                                      0.0,
                                                      0.0,
                                                      0.0,
                                                      9.64501953125,
                                                      0.0,
                                                      0.0,
                                                      0.0,
                                                      5.7317976951599121
                                                   ]
                                                },
                                                "content" : {
                                                   "uri" : "Tile_+000_+041_L21_0001130.b3dm"
                                                },
                                                "geometricError" : 0.76346081495285034,
                                                "refine" : "REPLACE"
                                             }
                                          ],
                                          "content" : {
                                             "uri" : "Tile_+000_+041_L20_000110t3.b3dm"
                                          },
                                          "geometricError" : 1.5269216299057007,
                                          "refine" : "REPLACE"
                                       },
                                       {
                                          "boundingVolume" : {
                                             "box" : [
                                                -9248.0771484375,
                                                4494.1982421875,
                                                20.780590057373047,
                                                20.14453125,
                                                0.0,
                                                0.0,
                                                0.0,
                                                18.882568359375,
                                                0.0,
                                                0.0,
                                                0.0,
                                                6.8754472732543945
                                             ]
                                          },
                                          "children" : [
                                             {
                                                "boundingVolume" : {
                                                   "box" : [
                                                      -9258.173828125,
                                                      4484.8193359375,
                                                      20.961122512817383,
                                                      9.98583984375,
                                                      0.0,
                                                      0.0,
                                                      0.0,
                                                      9.44140625,
                                                      0.0,
                                                      0.0,
                                                      0.0,
                                                      6.6949143409729004
                                                   ]
                                                },
                                                "content" : {
                                                   "uri" : "Tile_+000_+041_L21_0001200.b3dm"
                                                },
                                                "geometricError" : 0.75427323579788208,
                                                "refine" : "REPLACE"
                                             },
                                             {
                                                "boundingVolume" : {
                                                   "box" : [
                                                      -9258.173828125,
                                                      4503.57666015625,
                                                      18.286008834838867,
                                                      9.98583984375,
                                                      0.0,
                                                      0.0,
                                                      0.0,
                                                      9.44140625,
                                                      0.0,
                                                      0.0,
                                                      0.0,
                                                      3.8815293312072754
                                                   ]
                                                },
                                                "content" : {
                                                   "uri" : "Tile_+000_+041_L21_0001210.b3dm"
                                                },
                                                "geometricError" : 0.75427323579788208,
                                                "refine" : "REPLACE"
                                             },
                                             {
                                                "boundingVolume" : {
                                                   "box" : [
                                                      -9238.123046875,
                                                      4484.8193359375,
                                                      20.209623336791992,
                                                      10.18994140625,
                                                      0.0,
                                                      0.0,
                                                      0.0,
                                                      9.44140625,
                                                      0.0,
                                                      0.0,
                                                      0.0,
                                                      6.2325587272644043
                                                   ]
                                                },
                                                "content" : {
                                                   "uri" : "Tile_+000_+041_L21_0001220.b3dm"
                                                },
                                                "geometricError" : 0.75427323579788208,
                                                "refine" : "REPLACE"
                                             },
                                             {
                                                "boundingVolume" : {
                                                   "box" : [
                                                      -9238.123046875,
                                                      4503.57666015625,
                                                      18.982460021972656,
                                                      10.18994140625,
                                                      0.0,
                                                      0.0,
                                                      0.0,
                                                      9.44140625,
                                                      0.0,
                                                      0.0,
                                                      0.0,
                                                      4.6479387283325195
                                                   ]
                                                },
                                                "content" : {
                                                   "uri" : "Tile_+000_+041_L21_0001230.b3dm"
                                                },
                                                "geometricError" : 0.75427323579788208,
                                                "refine" : "REPLACE"
                                             }
                                          ],
                                          "content" : {
                                             "uri" : "Tile_+000_+041_L20_000120t3.b3dm"
                                          },
                                          "geometricError" : 1.5085464715957642,
                                          "refine" : "REPLACE"
                                       },
                                       {
                                          "boundingVolume" : {
                                             "box" : [
                                                -9248.0771484375,
                                                4531.8857421875,
                                                19.684110641479492,
                                                20.14453125,
                                                0.0,
                                                0.0,
                                                0.0,
                                                19.054931640625,
                                                0.0,
                                                0.0,
                                                0.0,
                                                5.2628569602966309
                                             ]
                                          },
                                          "children" : [
                                             {
                                                "boundingVolume" : {
                                                   "box" : [
                                                      -9258.173828125,
                                                      4522.333984375,
                                                      18.17582893371582,
                                                      9.98583984375,
                                                      0.0,
                                                      0.0,
                                                      0.0,
                                                      9.441162109375,
                                                      0.0,
                                                      0.0,
                                                      0.0,
                                                      3.7154979705810547
                                                   ]
                                                },
                                                "content" : {
                                                   "uri" : "Tile_+000_+041_L21_0001300.b3dm"
                                                },
                                                "geometricError" : 0.70300322771072388,
                                                "refine" : "REPLACE"
                                             },
                                             {
                                                "boundingVolume" : {
                                                   "box" : [
                                                      -9258.173828125,
                                                      4541.29541015625,
                                                      19.710132598876953,
                                                      9.98583984375,
                                                      0.0,
                                                      0.0,
                                                      0.0,
                                                      9.64501953125,
                                                      0.0,
                                                      0.0,
                                                      0.0,
                                                      5.251338005065918
                                                   ]
                                                },
                                                "content" : {
                                                   "uri" : "Tile_+000_+041_L21_0001310.b3dm"
                                                },
                                                "geometricError" : 0.70300322771072388,
                                                "refine" : "REPLACE"
                                             },
                                             {
                                                "boundingVolume" : {
                                                   "box" : [
                                                      -9238.123046875,
                                                      4522.333984375,
                                                      19.116064071655273,
                                                      10.18994140625,
                                                      0.0,
                                                      0.0,
                                                      0.0,
                                                      9.441162109375,
                                                      0.0,
                                                      0.0,
                                                      0.0,
                                                      4.6132278442382813
                                                   ]
                                                },
                                                "content" : {
                                                   "uri" : "Tile_+000_+041_L21_0001320.b3dm"
                                                },
                                                "geometricError" : 0.70300322771072388,
                                                "refine" : "REPLACE"
                                             },
                                             {
                                                "boundingVolume" : {
                                                   "box" : [
                                                      -9238.123046875,
                                                      4541.29541015625,
                                                      19.217006683349609,
                                                      10.18994140625,
                                                      0.0,
                                                      0.0,
                                                      0.0,
                                                      9.64501953125,
                                                      0.0,
                                                      0.0,
                                                      0.0,
                                                      4.7761869430541992
                                                   ]
                                                },
                                                "content" : {
                                                   "uri" : "Tile_+000_+041_L21_0001330.b3dm"
                                                },
                                                "geometricError" : 0.70300322771072388,
                                                "refine" : "REPLACE"
                                             }
                                          ],
                                          "content" : {
                                             "uri" : "Tile_+000_+041_L20_000130t3.b3dm"
                                          },
                                          "geometricError" : 1.4060064554214478,
                                          "refine" : "REPLACE"
                                       }
                                    ],
                                    "content" : {
                                       "uri" : "Tile_+000_+041_L19_00010t3.b3dm"
                                    },
                                    "geometricError" : 5.8086071014404297,
                                    "refine" : "REPLACE"
                                 }
                              ],
                              "content" : {
                                 "uri" : "Tile_+000_+041_L18_0000t1.b3dm"
                              },
                              "geometricError" : 23.077096939086914,
                              "refine" : "REPLACE"
                           }
                        ],
                        "content" : {
                           "uri" : "Tile_+000_+041_L17_000.b3dm"
                        },
                        "geometricError" : 69.463127136230469,
                        "refine" : "REPLACE"
                     }
                  ],
                  "content" : {
                     "uri" : "Tile_+000_+041_L16_00.b3dm"
                  },
                  "geometricError" : 138.92625427246094,
                  "refine" : "REPLACE"
               }
            ],
            "content" : {
               "uri" : "Tile_+000_+041_L15_0.b3dm"
            },
            "geometricError" : 277.85250854492188,
            "refine" : "REPLACE"
         }
      ],
      "content" : {
         "uri" : "root.b3dm"
      },
      "geometricError" : 73722.36328125,
      "refine" : "REPLACE"
   }
}
